NiukeFpgaGongchengshiQiuzhiJingyanFenxiang20212022Fix1/README.md
NiukeFpgaGongchengshiQiuzhiJingyanFenxiang20212022Fix1/__init__.py
NiukeFpgaGongchengshiQiuzhiJingyanFenxiang20212022Fix1/__main__.py
NiukeFpgaGongchengshiQiuzhiJingyanFenxiang20212022Fix1/file.epub
NiukeFpgaGongchengshiQiuzhiJingyanFenxiang20212022Fix1/index.html
NiukeFpgaGongchengshiQiuzhiJingyanFenxiang20212022Fix1/css/__init__.py
NiukeFpgaGongchengshiQiuzhiJingyanFenxiang20212022Fix1/css/annotations.css
NiukeFpgaGongchengshiQiuzhiJingyanFenxiang20212022Fix1/css/main.css
NiukeFpgaGongchengshiQiuzhiJingyanFenxiang20212022Fix1/css/normalize.css
NiukeFpgaGongchengshiQiuzhiJingyanFenxiang20212022Fix1/css/popup.css
NiukeFpgaGongchengshiQiuzhiJingyanFenxiang20212022Fix1/font/__init__.py
NiukeFpgaGongchengshiQiuzhiJingyanFenxiang20212022Fix1/font/fontello.eot
NiukeFpgaGongchengshiQiuzhiJingyanFenxiang20212022Fix1/font/fontello.svg
NiukeFpgaGongchengshiQiuzhiJingyanFenxiang20212022Fix1/font/fontello.ttf
NiukeFpgaGongchengshiQiuzhiJingyanFenxiang20212022Fix1/font/fontello.woff
NiukeFpgaGongchengshiQiuzhiJingyanFenxiang20212022Fix1/img/__init__.py
NiukeFpgaGongchengshiQiuzhiJingyanFenxiang20212022Fix1/img/annotator-glyph-sprite.png
NiukeFpgaGongchengshiQiuzhiJingyanFenxiang20212022Fix1/img/annotator-icon-sprite.png
NiukeFpgaGongchengshiQiuzhiJingyanFenxiang20212022Fix1/img/apple-touch-icon.png
NiukeFpgaGongchengshiQiuzhiJingyanFenxiang20212022Fix1/img/cancelfullscreen.png
NiukeFpgaGongchengshiQiuzhiJingyanFenxiang20212022Fix1/img/close.png
NiukeFpgaGongchengshiQiuzhiJingyanFenxiang20212022Fix1/img/fullscreen.png
NiukeFpgaGongchengshiQiuzhiJingyanFenxiang20212022Fix1/img/loader.gif
NiukeFpgaGongchengshiQiuzhiJingyanFenxiang20212022Fix1/img/menu-icon.png
NiukeFpgaGongchengshiQiuzhiJingyanFenxiang20212022Fix1/img/save.png
NiukeFpgaGongchengshiQiuzhiJingyanFenxiang20212022Fix1/img/saved.png
NiukeFpgaGongchengshiQiuzhiJingyanFenxiang20212022Fix1/img/settings-s.png
niuke_fpga_gongchengshi_qiuzhi_jingyan_fenxiang_2021_2022_fix1-2025.3.25.1.dist-info/METADATA
niuke_fpga_gongchengshi_qiuzhi_jingyan_fenxiang_2021_2022_fix1-2025.3.25.1.dist-info/WHEEL
niuke_fpga_gongchengshi_qiuzhi_jingyan_fenxiang_2021_2022_fix1-2025.3.25.1.dist-info/entry_points.txt
niuke_fpga_gongchengshi_qiuzhi_jingyan_fenxiang_2021_2022_fix1-2025.3.25.1.dist-info/top_level.txt
niuke_fpga_gongchengshi_qiuzhi_jingyan_fenxiang_2021_2022_fix1-2025.3.25.1.dist-info/RECORD
